{
  "turmas": [
    {
      "nome_turma": "1º ANO A",
      "alunos": [
        {
          "numero": "01",
          "nome": "Ana Julia Santana do Nascimento"
        },
        {
          "numero": "02",
          "nome": "Ana Paula Nascimento da Silva Dias"
        },
        {
          "numero": "03",
          "nome": "Anderson Ariel Alves da Silva"
        },
        {
          "numero": "04",
          "nome": "André Pablo Alves Pereira"
        },
        {
          "numero": "05",
          "nome": "Anna Lyvia de Lima Soares"
        },
        {
          "numero": "06",
          "nome": "Damasio Gutierry de Almeida Medeiros"
        },
        {
          "numero": "07",
          "nome": "Edson Cruz da Silva Netto"
        },
        {
          "numero": "08",
          "nome": "Eloi Davi Oliveira da Silva"
        },
        {
          "numero": "09",
          "nome": "Elyelson Gonçalves Gomes da Silva"
        },
        {
          "numero": "10",
          "nome": "Fatima Geisiele dos Santos Teixeira"
        },
        {
          "numero": "11",
          "nome": "Gabriel Inohana Leão"
        },
        {
          "numero": "12",
          "nome": "Geovana Alves de Lima"
        },
        {
          "numero": "13",
          "nome": "Guilherme Clemente dos Santos"
        },
        {
          "numero": "14",
          "nome": "Hayrton Alcântara da Cunha Filho"
        },
        {
          "numero": "15",
          "nome": "Kaleble de Souza Gomes"
        },
        {
          "numero": "16",
          "nome": "Lavínia Guedes da Costa"
        },
        {
          "numero": "17",
          "nome": "Marcella Santos da Silva"
        },
        {
          "numero": "18",
          "nome": "Maria Dariely dos Santos Teixeira"
        },
        {
          "numero": "19",
          "nome": "Maria Ester Soares Moreira"
        },
        {
          "numero": "20",
          "nome": "Maria Vitória Lima de Oliveira"
        },
        {
          "numero": "21",
          "nome": "Mikael Santos da Costa"
        },
        {
          "numero": "22",
          "nome": "Sofia Lacerda Castelo"
        },
        {
          "numero": "23",
          "nome": "Thaylane Viana Silva"
        },
        {
          "numero": "24",
          "nome": "Welvys Michel de Pontes Targino"
        }
      ]
    },
    {
      "nome_turma": "1º ANO B",
      "alunos": [
        {
          "numero": "01",
          "nome": "Adrielly dos Santos Rodrigues Lopes"
        },
        {
          "numero": "02",
          "nome": "Ana Vitória da Silva Felipe Cabral"
        },
        {
          "numero": "03",
          "nome": "Beatriz Renally Santiago Vieira"
        },
        {
          "numero": "04",
          "nome": "Bianca Silva Santos"
        },
        {
          "numero": "05",
          "nome": "Cauan Lucas Santos Bizerra"
        },
        {
          "numero": "06",
          "nome": "Elis Elailly Cândido da Silva"
        },
        {
          "numero": "07",
          "nome": "Emilly Rebeka Lima Santos"
        },
        {
          "numero": "08",
          "nome": "Gustavo Luna Bezerra"
        },
        {
          "numero": "09",
          "nome": "Helena Rodrigues Machado"
        },
        {
          "numero": "10",
          "nome": "Jardson Kildare Silva de Oliveira"
        },
        {
          "numero": "11",
          "nome": "Johann Julio de Almeida Santos"
        },
        {
          "numero": "12",
          "nome": "João Victor de Andrade Farias"
        },
        {
          "numero": "13",
          "nome": "Laryssa Soares dos Santos"
        },
        {
          "numero": "14",
          "nome": "Lucas Gabriel Macedo de Souza"
        },
        {
          "numero": "15",
          "nome": "Luis Eduardo de Souza"
        },
        {
          "numero": "16",
          "nome": "Luis Henrique de Souza"
        },
        {
          "numero": "17",
          "nome": "Maria Eduarda Araújo Silva"
        },
        {
          "numero": "18",
          "nome": "Maria Luiza Braz Costa"
        },
        {
          "numero": "19",
          "nome": "Mario Porfirio da Silva Júnior"
        },
        {
          "numero": "20",
          "nome": "Matheus Constatino Gomes"
        },
        {
          "numero": "21",
          "nome": "Maxsuel Ferreira da Costa"
        },
        {
          "numero": "22",
          "nome": "Maycon Leandro Nunes dos Santos"
        },
        {
          "numero": "23",
          "nome": "Pedro Gabriel Vicente Soares"
        },
        {
          "numero": "24",
          "nome": "Pedro Henrique Felix Pessoa"
        }
      ]
    },
    {
      "nome_turma": "1º ANO C",
      "alunos": [
        {
          "numero": "01",
          "nome": "Ana Eloiza Costa de Queiroz Silva"
        },
        {
          "numero": "02",
          "nome": "Anthony Belarmino Souza da Silva"
        },
        {
          "numero": "03",
          "nome": "Beatriz da Cruz Souza"
        },
        {
          "numero": "04",
          "nome": "Davi Flôr Pacheco de Oliveira"
        },
        {
          "numero": "05",
          "nome": "Davi Silva de Araújo"
        },
        {
          "numero": "06",
          "nome": "Delvo Neto Andrade Cunha"
        },
        {
          "numero": "07",
          "nome": "Diel de Paula Santos"
        },
        {
          "numero": "08",
          "nome": "Dominique da Costa Pereira de Almeida Souza"
        },
        {
          "numero": "09",
          "nome": "Higor Vicicius Cruz dos Santos"
        },
        {
          "numero": "10",
          "nome": "Josué Gonçalves Bezerra"
        },
        {
          "numero": "11",
          "nome": "João Miguel Estevão Veras Pessoa"
        },
        {
          "numero": "12",
          "nome": "Klara Gabriela Macedo Alves"
        },
        {
          "numero": "13",
          "nome": "Layanny Vitória Ferreira da Silva"
        },
        {
          "numero": "14",
          "nome": "Lucas Ferreira de Lira"
        },
        {
          "numero": "15",
          "nome": "Maria Gabriela Muniz de Souza"
        },
        {
          "numero": "16",
          "nome": "Maysa Gabrielly Andrade Barbosa"
        },
        {
          "numero": "17",
          "nome": "Miguel Ribeiro de Souza"
        },
        {
          "numero": "18",
          "nome": "Nicolly Nataly Barbosa Capiotto"
        },
        {
          "numero": "19",
          "nome": "Pedro Cauan Morais Araújo"
        },
        {
          "numero": "20",
          "nome": "Raul Vinicius Paulino de Menezes Lima"
        },
        {
          "numero": "21",
          "nome": "Rian Alves da Silva"
        },
        {
          "numero": "22",
          "nome": "Samuel Euzébio Farias"
        },
        {
          "numero": "23",
          "nome": "Sophia Garcia da Silva"
        },
        {
          "numero": "24",
          "nome": "Thaynná Evellen Silvestre de Brito"
        },
        {
          "numero": "25",
          "nome": "Wadrian Aranha Sales"
        },
        {
          "numero": "26",
          "nome": "Warlei Aranha Sales"
        }
      ]
    },
    {
      "nome_turma": "2º ANO A",
      "alunos": [
        {
          "numero": "01",
          "nome": "Alicia Natália Alves de Souza"
        },
        {
          "numero": "02",
          "nome": "Ana Beatriz Conceição Bandeira"
        },
        {
          "numero": "03",
          "nome": "Angeliny Pessoa dos Santos"
        },
        {
          "numero": "04",
          "nome": "Carlos Eduardo de Freitas Silvino"
        },
        {
          "numero": "05",
          "nome": "Davy Fernando Tavares Pinheiro Jacob"
        },
        {
          "numero": "06",
          "nome": "Diôgo dos Anjos Rodrigues"
        },
        {
          "numero": "07",
          "nome": "Elias Alves Barbosa"
        },
        {
          "numero": "08",
          "nome": "Enzo Gabriel Miguel dos Santos"
        },
        {
          "numero": "09",
          "nome": "Evelyn Silvino de Lima"
        },
        {
          "numero": "10",
          "nome": "Jordânia Lima da Costa"
        },
        {
          "numero": "11",
          "nome": "Kauã Gomes Firmino"
        },
        {
          "numero": "12",
          "nome": "Lara Bianca da Silva Batista"
        },
        {
          "numero": "13",
          "nome": "Leandro da Silva Fonseca Filho"
        },
        {
          "numero": "14",
          "nome": "Lorenna Gentil Peixoto"
        },
        {
          "numero": "15",
          "nome": "Louysy Sophia de Freitas Gomes"
        },
        {
          "numero": "16",
          "nome": "Lucyemille Fernandes dos Santos"
        },
        {
          "numero": "17",
          "nome": "Marielly Gabriela de Oliveira Freire"
        },
        {
          "numero": "18",
          "nome": "Messias de Oliveira Silva"
        },
        {
          "numero": "19",
          "nome": "Mirella Ferreira de França"
        },
        {
          "numero": "20",
          "nome": "Nicole Vitória Belarmino da Silva"
        },
        {
          "numero": "21",
          "nome": "Pedro Henrique Ricardo Moura do Nascimento"
        },
        {
          "numero": "22",
          "nome": "Pedro Henrique Rocha da Silva"
        },
        {
          "numero": "23",
          "nome": "Pérolla Vittória Oliveira Lima da Silva"
        },
        {
          "numero": "24",
          "nome": "Rhuan Carlos de Araújo Sousa"
        },
        {
          "numero": "25",
          "nome": "Thiago Gabriel de Lima Freire"
        },
        {
          "numero": "26",
          "nome": "Yasmim Lohane Muller Coelho"
        },
        {
          "numero": "27",
          "nome": "Yuri Martins de Souza"
        }
      ]
    },
    {
      "nome_turma": "2º ANO B",
      "alunos": [
        {
          "numero": "01",
          "nome": "Ana Luiza da Silva Nogueira"
        },
        {
          "numero": "02",
          "nome": "Anghellyna Victória Benevides Felizardo Costa"
        },
        {
          "numero": "03",
          "nome": "Arthur Kauã Ferreira Barbosa"
        },
        {
          "numero": "04",
          "nome": "Cícera Tayna Gomes Rocha"
        },
        {
          "numero": "05",
          "nome": "Davi de Souza Alves"
        },
        {
          "numero": "06",
          "nome": "Elias Gabriel Rocha Diniz"
        },
        {
          "numero": "07",
          "nome": "Emanuel Pedro do Egito Soares"
        },
        {
          "numero": "08",
          "nome": "Gabriela Souto da Trindade"
        },
        {
          "numero": "09",
          "nome": "Gabryelle Nayara Pereira de Sousa"
        },
        {
          "numero": "10",
          "nome": "Geovanna da Silva Freire"
        },
        {
          "numero": "11",
          "nome": "Isaac Sales Barbosa"
        },
        {
          "numero": "12",
          "nome": "Jonathan Caio Gonçalves de Lima"
        },
        {
          "numero": "13",
          "nome": "José Carlos de Freitas Souza"
        },
        {
          "numero": "14",
          "nome": "Joyce Kelly Bernado Correia"
        },
        {
          "numero": "15",
          "nome": "Júlia Vasconcelos da Silva Basílio Lucena"
        },
        {
          "numero": "16",
          "nome": "Karoliny Vitória Freire da Silva Nascimento"
        },
        {
          "numero": "17",
          "nome": "Letícia Monteiro Costa da Cruz"
        },
        {
          "numero": "18",
          "nome": "Lucas Costa Blanco"
        },
        {
          "numero": "19",
          "nome": "Maria Eduarda de Souza"
        },
        {
          "numero": "20",
          "nome": "Rafaela Guimarães Marques dos Santos"
        },
        {
          "numero": "21",
          "nome": "Roberto Pê"
        },
        {
          "numero": "22",
          "nome": "Sofiah Lara Bezerra Porto"
        },
        {
          "numero": "23",
          "nome": "Thuanny Vitória Duarte de Araújo"
        },
        {
          "numero": "24",
          "nome": "Victor Antonino Figueiredo da Silva"
        },
        {
          "numero": "25",
          "nome": "Welena Maria Ferreira da Silva"
        },
        {
          "numero": "26",
          "nome": "Wendel Ray Pereira Garcia"
        },
        {
          "numero": "27",
          "nome": "Yasmin Antonino Araújo"
        }
      ]
    },
    {
      "nome_turma": "2º ANO C",
      "alunos": [
        {
          "numero": "01",
          "nome": "Cauã Henrique Pereira da Silva"
        },
        {
          "numero": "02",
          "nome": "Iana Havenna Alves Lisboa"
        },
        {
          "numero": "03",
          "nome": "Ivina Priscylla Ribeiro Melo"
        },
        {
          "numero": "04",
          "nome": "José Krause de Freitas Filho"
        },
        {
          "numero": "05",
          "nome": "João Pedro do Nascimento Silva"
        },
        {
          "numero": "06",
          "nome": "Julia de Souza Santos do Rêgo"
        },
        {
          "numero": "07",
          "nome": "Jullya de Paiva Lopes"
        },
        {
          "numero": "08",
          "nome": "Kalyel Artur da Silva Martins"
        },
        {
          "numero": "09",
          "nome": "Kevin Lucas Leite de Sousa"
        },
        {
          "numero": "10",
          "nome": "Leandro Junio Lima da Costa"
        },
        {
          "numero": "11",
          "nome": "Lendryus Lima da Costa"
        },
        {
          "numero": "12",
          "nome": "Leonardo Aprigio Menezes dos Santos"
        },
        {
          "numero": "13",
          "nome": "Louhanna Micaelly Silva de Araújo"
        },
        {
          "numero": "14",
          "nome": "Luis Felipe Canteros Bezerra"
        },
        {
          "numero": "15",
          "nome": "Lyllian Maria Santana Luciano"
        },
        {
          "numero": "16",
          "nome": "Maria Clara de Lima Almeida"
        },
        {
          "numero": "17",
          "nome": "Nayara Kely Souza dos Santos"
        },
        {
          "numero": "18",
          "nome": "Pedro Henrique Maia Nascimento"
        },
        {
          "numero": "19",
          "nome": "Samuel Victor Cunha"
        },
        {
          "numero": "20",
          "nome": "Samuel Vinícius Felinto dos Santos"
        },
        {
          "numero": "21",
          "nome": "Stefanny Sabrini Falcão Dantas"
        },
        {
          "numero": "22",
          "nome": "Tayná Rodrigues Alves"
        },
        {
          "numero": "23",
          "nome": "Victor Emmanuel Macêdo Fidelis"
        },
        {
          "numero": "24",
          "nome": "Yasmin da Silva Ferreira"
        },
        {
          "numero": "25",
          "nome": "Ágatha Fernanda Leite Alves"
        }
      ]
    },
    {
      "nome_turma": "3º ANO A",
      "alunos": [
        {
          "numero": "01",
          "nome": "Agátha Fernanda Maciel de Souza"
        },
        {
          "numero": "02",
          "nome": "Aischa Leticia da Silva"
        },
        {
          "numero": "03",
          "nome": "Ana Luiza Alves dos Santos"
        },
        {
          "numero": "04",
          "nome": "Caio Lucas dos Santos"
        },
        {
          "numero": "05",
          "nome": "Davi Barbosa Oliveira"
        },
        {
          "numero": "06",
          "nome": "Enzo Henrique de Souza"
        },
        {
          "numero": "07",
          "nome": "Gabriel Henrique da Silva Santana"
        },
        {
          "numero": "08",
          "nome": "Giovanny Macedo Fidelis dos Santos"
        },
        {
          "numero": "09",
          "nome": "Ivanildo Paulo dos Santos Neto"
        },
        {
          "numero": "10",
          "nome": "Jakson Lopes de Azevedo"
        },
        {
          "numero": "11",
          "nome": "Katllyn Vitória Felismino dos Santos"
        },
        {
          "numero": "12",
          "nome": "Lanilson Pereira do Oriente Lino"
        },
        {
          "numero": "13",
          "nome": "Maria Flor Limeira Gomes"
        },
        {
          "numero": "14",
          "nome": "Maria Willyanna Santos da Silva"
        },
        {
          "numero": "15",
          "nome": "Mariana Paula Nunes dos Santos"
        },
        {
          "numero": "16",
          "nome": "Mikael da Silva Cunha"
        },
        {
          "numero": "17",
          "nome": "Natanel Monteiro Souza"
        },
        {
          "numero": "18",
          "nome": "Pedro Henrique Pereira Cunha"
        },
        {
          "numero": "19",
          "nome": "Roanderson Alixandre Prudencio Ribeiro"
        },
        {
          "numero": "20",
          "nome": "Talisson Fabricio Brito dos Santos"
        }
      ]
    },
    {
      "nome_turma": "3º ANO B",
      "alunos": [
        {
          "numero": "01",
          "nome": "Alex Bandeira Costa Junior"
        },
        {
          "numero": "02",
          "nome": "Ana Gabrielly Silva dos Santos"
        },
        {
          "numero": "03",
          "nome": "Ana Mirelly Fernandes de Lima"
        },
        {
          "numero": "04",
          "nome": "Arthur Vitor Alves de Sousa"
        },
        {
          "numero": "05",
          "nome": "Daniel de Vasconcelos Pereira"
        },
        {
          "numero": "06",
          "nome": "Elias Linhares da Silva"
        },
        {
          "numero": "07",
          "nome": "Guilherme Ciqueira de Araújo"
        },
        {
          "numero": "08",
          "nome": "Guilherme de Oliveira Andrade"
        },
        {
          "numero": "09",
          "nome": "Igor Henrique Fernandes da Silva"
        },
        {
          "numero": "10",
          "nome": "Ingrid Jamile Alves Oliveira"
        },
        {
          "numero": "11",
          "nome": "João Gabriel Silva Gois"
        },
        {
          "numero": "12",
          "nome": "Kariny Leandra Silva Nascimento"
        },
        {
          "numero": "13",
          "nome": "Lunna Lorena Barbosa Capiotto"
        },
        {
          "numero": "14",
          "nome": "Maria Regilane dos Santos Teixeira"
        },
        {
          "numero": "15",
          "nome": "Matheus Henrique Silva de Lima Santos"
        },
        {
          "numero": "16",
          "nome": "Pyetro Phelipe Mota de Souza"
        },
        {
          "numero": "17",
          "nome": "Rodrigo Santos Freire"
        },
        {
          "numero": "18",
          "nome": "Yasmin Caxias de Morais"
        }
      ]
    }
  ]
}